instant_coverage/__init__.py
instant_coverage/models.py
instant_coverage/optional.py
instant_coverage/type_utils.py
django_instant_coverage-1.2.1.dist-info/LICENSE
django_instant_coverage-1.2.1.dist-info/METADATA
django_instant_coverage-1.2.1.dist-info/WHEEL
django_instant_coverage-1.2.1.dist-info/top_level.txt
django_instant_coverage-1.2.1.dist-info/RECORD
