Metadata-Version: 2.1
Name: django-instant-coverage
Version: 1.2.1
Summary: Better-than-nothing testing for Django
Home-page: https://github.com/colons/instant-coverage
Author: colons
Author-email: pypi@colons.co
License: BSD
Platform: any
Classifier: Development Status :: 5 - Production/Stable
Classifier: Framework :: Django
Classifier: Intended Audience :: Developers
Classifier: License :: OSI Approved :: BSD License
Classifier: Operating System :: OS Independent
Classifier: Topic :: Software Development :: Testing
Classifier: Programming Language :: Python :: 2.7
Classifier: Programming Language :: Python :: 3
Requires-Dist: Django
Requires-Dist: mock
Requires-Dist: six
Requires-Dist: beautifulsoup4
Requires-Dist: requests
Requires-Dist: html5lib
Provides-Extra: linting
Requires-Dist: django-stubs ; extra == 'linting'
Requires-Dist: flake8 ; extra == 'linting'
Requires-Dist: flake8-import-order ; extra == 'linting'
Requires-Dist: mypy ; extra == 'linting'
Requires-Dist: types-beautifulsoup4 ; extra == 'linting'
Requires-Dist: types-html5lib ; extra == 'linting'
Requires-Dist: types-mock ; extra == 'linting'
Requires-Dist: types-requests ; extra == 'linting'
Requires-Dist: types-six ; extra == 'linting'
Requires-Dist: typing-extensions ; extra == 'linting'
Provides-Extra: testing
Requires-Dist: pyenchant ; extra == 'testing'
Requires-Dist: pytest ; extra == 'testing'
Requires-Dist: wcag-zoo (>=0.2.0) ; extra == 'testing'
